[
  {
    "co_owners": null,
    "keepers": null,
    "league_id": "1048889097223266304",
    "metadata": {
      "record": "LWLLWWLLWWLWWL",
      "streak": "1L"
    },
    "owner_id": "510013812276232192",
    "player_map": null,
    "players": [
      "10219",
      "10871",
      "10914",
      "11539",
      "11573",
      "11575",
      "11603",
      "11687",
      "11959",
      "1234",
      "1466",
      "1689",
      "3321",
      "4035",
      "4881",
      "4988",
      "5892",
      "5927",
      "5991",
      "6149",
      "6828",
      "6888",
      "6945",
      "7496",
      "8110",
      "8138",
      "8280",
      "8676",
      "8917",
      "9488",
      "9997",
      "MIN"
    ],
    "reserve": [
      "5892",
      "8676"
    ],
    "roster_id": 1,
    "settings": {
      "fpts": 2158,
      "fpts_against": 2010,
      "fpts_against_decimal": 30,
      "fpts_decimal": 14,
      "losses": 7,
      "ppts": 2360,
      "ppts_decimal": 34,
      "ties": 0,
      "total_moves": 0,
      "waiver_budget_used": 438,
      "waiver_position": 5,
      "wins": 7
    },
    "starters": [
      "4881",
      "8138",
      "6945",
      "3321",
      "5927",
      "9488",
      "1466",
      "9997",
      "11539",
      "MIN",
      "8280",
      "10914",
      "0"
    ],
    "taxi": [
      "11573",
      "11575",
      "11603",
      "11959"
    ]
  },
  {
    "co_owners": null,
    "keepers": null,
    "league_id": "1048889097223266304",
    "metadata": {
      "record": "LWWWWWLWWWWLWW",
      "streak": "2W"
    },
    "owner_id": "575194626101170176",
    "player_map": null,
    "players": [
      "10444",
      "11370",
      "11574",
      "11599",
      "11623",
      "11646",
      "1264",
      "3286",
      "4037",
      "4217",
      "4234",
      "4892",
      "4971",
      "4981",
      "5096",
      "5967",
      "6770",
      "6813",
      "7528",
      "7593",
      "7607",
      "7672",
      "8129",
      "8146",
      "8167",
      "8230",
      "9228",
      "9481",
      "9484",
      "9486",
      "9493",
      "KC"
    ],
    "reserve": [
      "10444",
      "4037"
    ],
    "roster_id": 2,
    "settings": {
      "fpts": 2132,
      "fpts_against": 1849,
      "fpts_against_decimal": 82,
      "fpts_decimal": 88,
      "losses": 3,
      "ppts": 2415,
      "ppts_decimal": 72,
      "ties": 0,
      "total_moves": 0,
      "waiver_budget_used": 500,
      "waiver_position": 12,
      "wins": 11
    },
    "starters": [
      "6770",
      "7528",
      "6813",
      "9493",
      "8146",
      "4981",
      "4217",
      "9486",
      "0",
      "0",
      "0",
      "7672",
      "4971"
    ],
    "taxi": [
      "11574",
      "11599",
      "11623",
      "11646"
    ]
  },
  {
    "co_owners": null,
    "keepers": null,
    "league_id": "1048889097223266304",
    "metadata": {
      "record": "LWLLLLWLLLWWWL",
      "streak": "1L"
    },
    "owner_id": "575406354368348160",
    "player_map": null,
    "players": [
      "10236",
      "11582",
      "11595",
      "11618",
      "11647",
      "2311",
      "3451",
      "4040",
      "4068",
      "4081",
      "4098",
      "4137",
      "4219",
      "4274",
      "5012",
      "5346",
      "5849",
      "5937",
      "6151",
      "6768",
      "6794",
      "6803",
      "8137",
      "8142",
      "8147",
      "8188",
      "8205",
      "8408",
      "9506",
      "DEN",
      "MIA"
    ],
    "reserve": [
      "6151",
      "6803"
    ],
    "roster_id": 3,
    "settings": {
      "fpts": 1895,
      "fpts_against": 2024,
      "fpts_against_decimal": 4,
      "fpts_decimal": 58,
      "losses": 9,
      "ppts": 2237,
      "ppts_decimal": 54,
      "ties": 0,
      "total_moves": 0,
      "waiver_budget_used": 500,
      "waiver_position": 6,
      "wins": 5
    },
    "starters": [
      "5849",
      "8205",
      "4137",
      "6794",
      "4274",
      "11618",
      "5012",
      "10236",
      "3451",
      "DEN",
      "2311",
      "5346",
      "4081"
    ],
    "taxi": [
      "11582",
      "11595",
      "11647"
    ]
  },
  {
    "co_owners": null,
    "keepers": null,
    "league_id": "1048889097223266304",
    "metadata": {
      "p_nick_2505": "I am the Wallerus",
      "p_nick_4017": "Also a Bum",
      "p_nick_5248": "Gus Bus",
      "p_nick_5859": "Spicy",
      "p_nick_5880": "",
      "p_nick_6801": "My Name's Not Tatoo! It's",
      "p_nick_6805": "Christmas",
      "p_nick_6814": "Hasta Baby",
      "p_nick_6849": "My Younger Brother's Better",
      "p_nick_6853": "Probably Related to Thomas",
      "p_nick_7571": "Headmaster",
      "p_nick_7588": "Bum who fumbles",
      "p_nick_7610": "Bum",
      "p_nick_8155": "Residential",
      "p_nick_8171": "Soon to be a Free Agent",
      "p_nick_8195": "He's All Yours Blake",
      "p_nick_947": "I'm Old",
      "record": "WLLLLWLLLLLLLL",
      "streak": "8L"
    },
    "owner_id": "575878107617718272",
    "player_map": null,
    "players": [
      "10222",
      "10235",
      "10905",
      "11560",
      "11571",
      "11581",
      "11592",
      "11600",
      "11630",
      "11638",
      "11792",
      "2359",
      "3678",
      "4082",
      "5332",
      "5859",
      "6801",
      "6804",
      "6826",
      "7571",
      "7588",
      "7640",
      "7670",
      "8126",
      "8131",
      "8155",
      "8210",
      "9494",
      "9509",
      "96",
      "CIN"
    ],
    "reserve": [
      "11581"
    ],
    "roster_id": 4,
    "settings": {
      "fpts": 1850,
      "fpts_against": 2233,
      "fpts_against_decimal": 2,
      "fpts_decimal": 62,
      "losses": 12,
      "ppts": 2248,
      "ppts_decimal": 24,
      "ties": 0,
      "total_moves": 0,
      "waiver_budget_used": 139,
      "waiver_position": 4,
      "wins": 2
    },
    "starters": [
      "6804",
      "2359",
      "8155",
      "6801",
      "5859",
      "10222",
      "8210",
      "9509",
      "3678",
      "CIN",
      "7640",
      "5332",
      "10905"
    ],
    "taxi": [
      "11560",
      "11592",
      "11630",
      "11638"
    ]
  },
  {
    "co_owners": null,
    "keepers": null,
    "league_id": "1048889097223266304",
    "metadata": {
      "record": "LLWLLWWWWLWLLW",
      "streak": "1W"
    },
    "owner_id": "510215233736572928",
    "player_map": null,
    "players": [
      "10213",
      "11435",
      "11439",
      "11596",
      "11616",
      "11643",
      "11655",
      "11729",
      "1945",
      "2749",
      "3214",
      "3294",
      "4018",
      "4034",
      "4046",
      "4070",
      "4199",
      "4574",
      "5848",
      "5947",
      "6183",
      "6938",
      "7525",
      "7526",
      "7547",
      "7562",
      "7694",
      "8119",
      "8202",
      "8348",
      "9511",
      "ARI"
    ],
    "reserve": [
      "3294",
      "4034"
    ],
    "roster_id": 5,
    "settings": {
      "fpts": 2035,
      "fpts_against": 2034,
      "fpts_against_decimal": 86,
      "fpts_decimal": 94,
      "losses": 7,
      "ppts": 2257,
      "ppts_decimal": 46,
      "ties": 0,
      "total_moves": 0,
      "waiver_budget_used": 375,
      "waiver_position": 8,
      "wins": 7
    },
    "starters": [
      "4046",
      "4018",
      "4199",
      "7547",
      "5947",
      "7525",
      "3214",
      "11655",
      "1945",
      "ARI",
      "6183",
      "4070",
      "8348"
    ],
    "taxi": [
      "11596",
      "11616",
      "11643",
      "11729"
    ]
  },
  {
    "co_owners": null,
    "keepers": null,
    "league_id": "1048889097223266304",
    "metadata": {
      "record": "WLWLLLWWLWWWWW",
      "streak": "5W"
    },
    "owner_id": "415249306090479616",
    "player_map": null,
    "players": [
      "10229",
      "10232",
      "11562",
      "11579",
      "11584",
      "11589",
      "11637",
      "11789",
      "2374",
      "2393",
      "4033",
      "4135",
      "421",
      "4351",
      "4663",
      "4984",
      "5086",
      "5580",
      "5844",
      "6130",
      "7049",
      "7543",
      "7608",
      "8225",
      "8259",
      "8392",
      "9226",
      "9500",
      "9999",
      "ATL",
      "DET",
      "PHI"
    ],
    "reserve": [
      "10229",
      "4663"
    ],
    "roster_id": 6,
    "settings": {
      "fpts": 1976,
      "fpts_against": 1860,
      "fpts_against_decimal": 38,
      "fpts_decimal": 12,
      "losses": 5,
      "ppts": 2296,
      "ppts_decimal": 8,
      "ties": 0,
      "total_moves": 0,
      "waiver_budget_used": 500,
      "waiver_position": 7,
      "wins": 9
    },
    "starters": [
      "4984",
      "9226",
      "7543",
      "9500",
      "7049",
      "11637",
      "5844",
      "11584",
      "8259",
      "ATL",
      "2393",
      "5580",
      "8392"
    ],
    "taxi": [
      "11562",
      "11579",
      "11589",
      "11789"
    ]
  },
  {
    "co_owners": null,
    "keepers": null,
    "league_id": "1048889097223266304",
    "metadata": {
      "record": "LLWWLLWLLWLLLL",
      "streak": "4L"
    },
    "owner_id": "792312710317572096",
    "player_map": null,
    "players": [
      "10225",
      "11421",
      "11570",
      "11597",
      "11610",
      "11615",
      "11625",
      "11629",
      "1166",
      "11895",
      "1233",
      "3233",
      "4147",
      "4195",
      "4454",
      "4999",
      "5133",
      "5185",
      "5857",
      "5906",
      "5987",
      "6797",
      "6819",
      "7561",
      "8117",
      "8132",
      "9221",
      "9497",
      "9501",
      "GB"
    ],
    "reserve": [
      "7561"
    ],
    "roster_id": 7,
    "settings": {
      "fpts": 1572,
      "fpts_against": 1958,
      "fpts_against_decimal": 56,
      "fpts_decimal": 64,
      "losses": 10,
      "ppts": 1833,
      "ppts_decimal": 88,
      "ties": 0,
      "total_moves": 0,
      "waiver_budget_used": 408,
      "waiver_position": 2,
      "wins": 4
    },
    "starters": [
      "6797",
      "5987",
      "9221",
      "9501",
      "6819",
      "8117",
      "5857",
      "11610",
      "4195",
      "GB",
      "4999",
      "1233",
      "3233"
    ],
    "taxi": [
      "11570",
      "11629"
    ]
  },
  {
    "co_owners": null,
    "keepers": null,
    "league_id": "1048889097223266304",
    "metadata": {
      "allow_pn_inactive_starters": "off",
      "allow_pn_player_injury_status": "off",
      "allow_pn_scoring": "off",
      "p_nick_10444": ".5 2end rounder",
      "p_nick_1234": ".5 2end rounder",
      "p_nick_1373": ".5 2end rounder",
      "p_nick_4033": "Late 1st rounder",
      "p_nick_4068": ". 5 2end rounder",
      "p_nick_4080": ". 5 2025 2end rounder",
      "p_nick_4089": ".5 2end rounder",
      "p_nick_5045": "",
      "p_nick_6943": "2024 2end",
      "p_nick_7568": ".5 2end rounder",
      "p_nick_7601": ".5 2end rounder",
      "p_nick_8116": ".5 2025 3rd rounder",
      "record": "WWLWWLLWWWLWWW",
      "restrict_pn_scoring_starters_only": "on",
      "streak": "3W"
    },
    "owner_id": "792563831732838400",
    "player_map": null,
    "players": [
      "10223",
      "10226",
      "11566",
      "11626",
      "11627",
      "11628",
      "11632",
      "11636",
      "11645",
      "11649",
      "11748",
      "11783",
      "1339",
      "1373",
      "3973",
      "4227",
      "5010",
      "5045",
      "6216",
      "6650",
      "6815",
      "7021",
      "7564",
      "7567",
      "7611",
      "8130",
      "8139",
      "8154",
      "8180",
      "8207",
      "9492",
      "IND"
    ],
    "reserve": [
      "11748",
      "8139"
    ],
    "roster_id": 8,
    "settings": {
      "fpts": 2060,
      "fpts_against": 1833,
      "fpts_against_decimal": 74,
      "fpts_decimal": 98,
      "losses": 4,
      "ppts": 2272,
      "ppts_decimal": 76,
      "ties": 0,
      "total_moves": 0,
      "waiver_budget_used": 500,
      "waiver_position": 9,
      "wins": 10
    },
    "starters": [
      "11566",
      "8154",
      "7021",
      "7564",
      "5045",
      "11632",
      "8130",
      "7611",
      "6650",
      "IND",
      "3973",
      "6815",
      "6216"
    ],
    "taxi": [
      "11626",
      "11627",
      "11636",
      "11645"
    ]
  },
  {
    "co_owners": null,
    "keepers": null,
    "league_id": "1048889097223266304",
    "metadata": {
      "record": "LWLWWWLWLLLLWL",
      "streak": "1L"
    },
    "owner_id": "793977545186979840",
    "player_map": null,
    "players": [
      "10888",
      "11563",
      "11576",
      "11620",
      "11631",
      "11635",
      "11651",
      "11669",
      "2133",
      "2197",
      "3163",
      "4066",
      "4666",
      "4960",
      "4967",
      "5248",
      "5840",
      "6039",
      "6783",
      "7090",
      "7600",
      "7839",
      "8121",
      "8183",
      "8228",
      "8289",
      "8339",
      "9482",
      "BAL",
      "BUF",
      "LAC",
      "SF"
    ],
    "reserve": [
      "4066",
      "8289"
    ],
    "roster_id": 9,
    "settings": {
      "fpts": 1851,
      "fpts_against": 1968,
      "fpts_against_decimal": 54,
      "fpts_decimal": 32,
      "losses": 8,
      "ppts": 2215,
      "ppts_decimal": 76,
      "ties": 0,
      "total_moves": 0,
      "waiver_budget_used": 378,
      "waiver_position": 11,
      "wins": 6
    },
    "starters": [
      "3163",
      "8228",
      "11651",
      "11631",
      "11635",
      "2133",
      "7600",
      "7090",
      "0",
      "LAC",
      "5840",
      "4960",
      "8339"
    ],
    "taxi": [
      "11563",
      "11576",
      "11620",
      "11669"
    ]
  },
  {
    "co_owners": null,
    "keepers": null,
    "league_id": "1048889097223266304",
    "metadata": {
      "p_nick_10892": "The Terminator",
      "p_nick_11584": "Bucky",
      "p_nick_3294": "Dak To The Future",
      "p_nick_4077": "The Adams Family",
      "p_nick_4866": "SaQuads",
      "p_nick_4983": "DJ",
      "p_nick_4988": "Chubba Lubba Dubb Dubb",
      "p_nick_5041": "All-Pro Fred",
      "p_nick_5916": "HenderSZN",
      "p_nick_6786": "CeeDees TDs",
      "p_nick_7523": "Sunshine",
      "p_nick_7553": "Unicorn",
      "p_nick_7569": "Big Nico",
      "p_nick_7839": "Money Mac",
      "p_nick_8111": "Bold move (C.Otton)",
      "p_nick_8119": "jaHan Solo",
      "p_nick_8148": "Jamo",
      "p_nick_8151": "K9",
      "p_nick_8172": "Dulcich de leche",
      "p_nick_9229": "AR15",
      "p_nick_9753": "Charbo",
      "p_nick_CLE": "Dawg Pound",
      "p_nick_NYJ": "Gang Green",
      "record": "WLWWWWLWWLWWLW",
      "streak": "1W"
    },
    "owner_id": "861064424906158080",
    "player_map": null,
    "players": [
      "10859",
      "11564",
      "11565",
      "11617",
      "11633",
      "11640",
      "4866",
      "4983",
      "5041",
      "5341",
      "5816",
      "6271",
      "6786",
      "7042",
      "7523",
      "7553",
      "7569",
      "8111",
      "8112",
      "8136",
      "8143",
      "8144",
      "8148",
      "8151",
      "8220",
      "8255",
      "9224",
      "9229",
      "9753",
      "9757",
      "LAR",
      "NYJ"
    ],
    "reserve": [
      "6786",
      "7523"
    ],
    "roster_id": 10,
    "settings": {
      "fpts": 2152,
      "fpts_against": 1871,
      "fpts_against_decimal": 42,
      "fpts_decimal": 26,
      "losses": 4,
      "ppts": 2515,
      "ppts_decimal": 24,
      "ties": 0,
      "total_moves": 0,
      "waiver_budget_used": 500,
      "waiver_position": 3,
      "wins": 10
    },
    "starters": [
      "11564",
      "4866",
      "9224",
      "7569",
      "8148",
      "8112",
      "10859",
      "9753",
      "7042",
      "LAR",
      "5816",
      "5041",
      "5341"
    ],
    "taxi": [
      "11565",
      "11617",
      "11633",
      "11640"
    ]
  },
  {
    "co_owners": null,
    "keepers": null,
    "league_id": "1048889097223266304",
    "metadata": {
      "p_nick_1426": "Roid Rage",
      "p_nick_2216": "",
      "p_nick_2449": "I'm Him!",
      "p_nick_3198": "Long Live the King",
      "p_nick_4950": "Kitty Kat Kirk",
      "p_nick_5850": "Jingleheymer Smith",
      "p_nick_5870": "Dimes",
      "p_nick_5906": "Hard Knox ",
      "p_nick_6783": "Judge Jeudy",
      "p_nick_6813": "Pick It Up",
      "p_nick_6904": "Hurts So Good",
      "p_nick_6938": "Ben Simmons",
      "p_nick_7042": "Bassmaster Classic",
      "p_nick_8290": "Young Deion",
      "p_nick_NE": "Bill",
      "record": "WLWWWLWLWWWWLW",
      "streak": "1W"
    },
    "owner_id": "510254202180411392",
    "player_map": null,
    "players": [
      "11533",
      "11567",
      "11583",
      "11650",
      "11834",
      "1426",
      "1479",
      "2216",
      "2309",
      "2449",
      "3172",
      "3198",
      "4039",
      "4144",
      "4943",
      "4950",
      "5022",
      "5850",
      "5862",
      "6302",
      "6904",
      "6911",
      "6943",
      "7594",
      "8134",
      "8150",
      "8160",
      "9480",
      "9487",
      "9504",
      "9756",
      "SEA"
    ],
    "reserve": [
      "2449",
      "4950"
    ],
    "roster_id": 11,
    "settings": {
      "fpts": 2263,
      "fpts_against": 2081,
      "fpts_against_decimal": 96,
      "fpts_decimal": 16,
      "losses": 4,
      "ppts": 2618,
      "ppts_decimal": 74,
      "ties": 0,
      "total_moves": 0,
      "waiver_budget_used": 500,
      "waiver_position": 10,
      "wins": 10
    },
    "starters": [
      "4943",
      "3198",
      "8150",
      "2216",
      "1479",
      "9756",
      "4144",
      "5850",
      "11533",
      "SEA",
      "3172",
      "6302",
      "6911"
    ],
    "taxi": [
      "11567",
      "11583",
      "11650",
      "11834"
    ]
  },
  {
    "co_owners": null,
    "keepers": null,
    "league_id": "1048889097223266304",
    "metadata": {
      "record": "WWLLLLWLLLLLLL",
      "streak": "7L"
    },
    "owner_id": "865653448849391616",
    "player_map": null,
    "players": [
      "10866",
      "11058",
      "11559",
      "11577",
      "11586",
      "11604",
      "11619",
      "11621",
      "11624",
      "5001",
      "5846",
      "5872",
      "5995",
      "6788",
      "6790",
      "6806",
      "6820",
      "6845",
      "6963",
      "7591",
      "7596",
      "7648",
      "7828",
      "8125",
      "8265",
      "9225",
      "9227",
      "9502",
      "9508",
      "9754",
      "9758",
      "PIT"
    ],
    "reserve": [
      "6845"
    ],
    "roster_id": 12,
    "settings": {
      "fpts": 1769,
      "fpts_against": 1992,
      "fpts_against_decimal": 42,
      "fpts_decimal": 42,
      "losses": 11,
      "ppts": 2091,
      "ppts_decimal": 34,
      "ties": 0,
      "total_moves": 0,
      "waiver_budget_used": 8,
      "waiver_position": 1,
      "wins": 3
    },
    "starters": [
      "9758",
      "6790",
      "9225",
      "5846",
      "5872",
      "11624",
      "11604",
      "9508",
      "11058",
      "PIT",
      "8265",
      "7648",
      "6788"
    ],
    "taxi": [
      "11559",
      "11577",
      "11619",
      "11621"
    ]
  }
]